[
  {
    "update": "2033 new cases, 3982 recoveries and 48 deaths in Delhi\n397 recoveries in Assam\n111 new cases and 107 recoveries in Chhattisgarh\n136 new cases and 51 recoveries in Goa\n",
    "timestamp": 1594224632
  },
  {
    "update": "1924 new cases, 992 recoveries and 11 deaths in Telangana\n",
    "timestamp": 1594225541
  },
  {
    "update": "9 new cases and 12 recoveries in Himachal Pradesh\n",
    "timestamp": 1594226731
  },
  {
    "update": "2 new cases in Meghalaya\n",
    "timestamp": 1594228162
  },
  {
    "update": "78 new cases in Jharkhand\n57 new cases in Tripura\n2 new cases in Mizoram\n",
    "timestamp": 1594228704
  },
  {
    "update": "66 recoveries in Jharkhand\n",
    "timestamp": 1594230339
  },
  {
    "update": "696 new cases in Assam\n",
    "timestamp": 1594231816
  },
  {
    "update": "11 new cases and 4 recoveries in Arunachal Pradesh\n",
    "timestamp": 1594237059
  },
  {
    "update": "3 new cases in Nagaland\n2 new cases in Andaman and Nicobar Islands\n",
    "timestamp": 1594267830
  },
  {
    "update": "577 new cases in Odisha\n",
    "timestamp": 1594271881
  },
  {
    "update": "149 new cases, 11 recoveries and 7 deaths in Rajasthan\n",
    "timestamp": 1594273512
  },
  {
    "update": "6 deaths in Odisha\n49 new cases, 35 recoveries and 2 deaths in Puducherry\n",
    "timestamp": 1594274155
  },
  {
    "update": "2 deaths in Assam\n",
    "timestamp": 1594277748
  },
  {
    "update": "58 new cases in Jharkhand\n",
    "timestamp": 1594279107
  },
  {
    "update": "3 new cases in Meghalaya\n",
    "timestamp": 1594280143
  },
  {
    "update": "1 recovery in Himachal Pradesh\n",
    "timestamp": 1594280725
  },
  {
    "update": "314 new cases and 31 recoveries in Haryana\n",
    "timestamp": 1594281331
  },
  {
    "update": "1555 new cases, 1053 recoveries and 13 deaths in Andhra Pradesh\n",
    "timestamp": 1594285724
  },
  {
    "update": "704 new cases in Bihar\n",
    "timestamp": 1594287935
  },
  {
    "update": "9 new cases in Meghalaya\n",
    "timestamp": 1594292952
  },
  {
    "update": "3 recoveries in Andaman and Nicobar Islands\n",
    "timestamp": 1594294572
  },
  {
    "update": "8 new cases and 27 recoveries in Ladakh\n3 new cases and 5 recoveries in Dadra and Nagar Haveli and Daman and Diu\n",
    "timestamp": 1594296698
  },
  {
    "update": "13 new cases in Nagaland\n",
    "timestamp": 1594297488
  },
  {
    "update": "401 recoveries in Odisha\n4 recoveries in Himachal Pradesh\n",
    "timestamp": 1594298197
  },
  {
    "update": "16 new cases and 1 recovery in Chandigarh\n",
    "timestamp": 1594298758
  },
  {
    "update": "251 recoveries and 136 deaths in Bihar\n",
    "timestamp": 1594300168
  },
  {
    "update": "360 new cases, 368 recoveries and 5 deaths in Haryana\n",
    "timestamp": 1594302343
  },
  {
    "update": "233 new cases, 117 recoveries and 5 deaths in Punjab\n339 new cases and 149 recoveries in Kerala\n11 new cases and 4 recoveries in Dadra and Nagar Haveli and Daman and Diu\n1 new case in Meghalaya\n",
    "timestamp": 1594302936
  },
  {
    "update": "6875 new cases, 4067 recoveries and 219 deaths in Maharashtra\n305 new cases, 245 recoveries and 5 deaths in Madhya Pradesh\n47 new cases and 22 recoveries in Uttarakhand\n1 new case in Sikkim\n",
    "timestamp": 1594304367
  },
  {
    "update": "957 recoveries and 17 deaths in Karnataka\n1088 new cases, 535 recoveries and 27 deaths in West Bengal\n",
    "timestamp": 1594305388
  },
  {
    "update": "4231 new cases, 3994 recoveries and 65 deaths in Tamil Nadu\n",
    "timestamp": 1594305983
  },
  {
    "update": "2228 new cases in Karnataka\n",
    "timestamp": 1594306567
  },
  {
    "update": "2187 new cases, 4027 recoveries and 45 deaths in Delhi\n",
    "timestamp": 1594307412
  },
  {
    "update": "861 new cases, 429 recoveries and 15 deaths in Gujarat\n",
    "timestamp": 1594307926
  },
  {
    "update": "240 new cases, 128 recoveries and 5 deaths in Jammu and Kashmir\n112 new cases, 66 recoveries and 1 death in Goa\n",
    "timestamp": 1594309026
  },
  {
    "update": "351 new cases, 193 recoveries and 2 deaths in Rajasthan\n153 new cases, 68 recoveries and 1 death in Chhattisgarh\n15 new cases and 6 recoveries in Manipur\n39 new cases and 8 recoveries in Himachal Pradesh\n",
    "timestamp": 1594311092
  },
  {
    "update": "421 recoveries and 3 deaths in Assam\n5 new cases and 6 recoveries in Andaman and Nicobar Islands\n",
    "timestamp": 1594311688
  },
  {
    "update": "1206 new cases, 796 recoveries and 17 deaths in Uttar Pradesh\n1410 new cases, 913 recoveries and 7 deaths in Telangana\n",
    "timestamp": 1594313155
  },
  {
    "update": "16 new cases in Tripura\n",
    "timestamp": 1594313787
  },
  {
    "update": "79 new cases in Goa\n14 recoveries in Tripura\n",
    "timestamp": 1594316248
  },
  {
    "update": "76 new cases, 40 recoveries and 1 death in Jharkhand\n",
    "timestamp": 1594316807
  },
  {
    "update": "15 new cases and 11 recoveries in Arunachal Pradesh\n",
    "timestamp": 1594318281
  },
  {
    "update": "568 new cases in Assam\n",
    "timestamp": 1594318774
  },
  {
    "update": "22 new cases in Mizoram\n",
    "timestamp": 1594346177
  },
  {
    "update": "23 new cases in Nagaland\n",
    "timestamp": 1594354150
  },
  {
    "update": "72 new cases, 18 recoveries and 1 death in Puducherry\n",
    "timestamp": 1594357720
  },
  {
    "update": "115 new cases, 70 recoveries and 4 deaths in Rajasthan\n755 new cases in Odisha\n",
    "timestamp": 1594358860
  },
  {
    "update": "4 deaths in Odisha\n1 new case in Mizoram\n",
    "timestamp": 1594359329
  },
  {
    "update": "2 deaths in Odisha\n",
    "timestamp": 1594359927
  },
  {
    "update": "28 new cases in Meghalaya\n",
    "timestamp": 1594361990
  }
]